hdfs_pyarrow_wrapper/__init__.py
hdfs_pyarrow_wrapper/hdfs_client_test.py
hdfs_pyarrow_wrapper/hdfs_utils.py
hdfs_pyarrow_wrapper-0.1.3.dist-info/METADATA
hdfs_pyarrow_wrapper-0.1.3.dist-info/WHEEL
hdfs_pyarrow_wrapper-0.1.3.dist-info/top_level.txt
hdfs_pyarrow_wrapper-0.1.3.dist-info/RECORD
