Metadata-Version: 2.1
Name: hdfs-pyarrow-wrapper
Version: 0.1.3
Summary: A wrapper for the HDFS API, using pyarrow
Author: Zhang Xin
Author-email: xinzhang.hello@gmail.com
Classifier: Programming Language :: Python :: 3
Classifier: License :: OSI Approved :: MIT License
Classifier: Operating System :: OS Independent
Requires-Python: >=3.6
